itdpy/auth.py
itdpy/client.py
itdpy/validate.py
itdpy/api/__init__.py
itdpy/api/clans.py
itdpy/api/comments.py
itdpy/api/files.py
itdpy/api/notifications.py
itdpy/api/posts.py
itdpy/api/profile.py
itdpy/api/users.py
itdpy/models/__init__.py
itdpy/models/actor.py
itdpy/models/attachment.py
itdpy/models/base.py
itdpy/models/comment.py
itdpy/models/comments.py
itdpy/models/me.py
itdpy/models/notification.py
itdpy/models/notifications.py
itdpy/models/post.py
itdpy/models/posts.py
itdpy/models/user.py
itdpy/models/user_lite.py
itdpy/models/users.py
itdpy-0.2.2.dist-info/licenses/LICENSE
itdpy-0.2.2.dist-info/METADATA
itdpy-0.2.2.dist-info/WHEEL
itdpy-0.2.2.dist-info/top_level.txt
itdpy-0.2.2.dist-info/RECORD
