Metadata-Version: 2.4
Name: itdpy
Version: 0.2.2
Summary: Python SDK for ИТД.com API
Author: Gam5510
License: MIT
Project-URL: Homepage, https://github.com/Gam5510/ITDpy
Project-URL: Repository, https://github.com/Gam5510/ITDpy
Requires-Python: >=3.9
License-File: LICENSE
Requires-Dist: requests>=2.28.0
Dynamic: license-file
